{
   "type": "mysql",
   "host": "localhost",
   "port": 3306,
   "username": "root",
   "password": "123456",
   "database": "test",
   "synchronize": true,
   "logging": false,
   "entities": [
      "src/api/models/**/*.ts"
   ],
   "migrations": [
      "src/api/migrations/**/*.ts"
   ],
   "subscribers": [
      "src/api/subscriber/**/*.ts"
   ],
   "cli": {
      "entitiesDir": "src/api/models",
      "migrationsDir": "src/api/migration",
      "subscribersDir": "src/api/subscriber"
   }
}